md_hierarchy/__init__.py
md_hierarchy/cli.py
md_hierarchy/merge.py
md_hierarchy/parser.py
md_hierarchy/split.py
md_hierarchy/types.py
md_hierarchy/utils.py
md_hierarchy-0.2.0.dist-info/METADATA
md_hierarchy-0.2.0.dist-info/WHEEL
md_hierarchy-0.2.0.dist-info/entry_points.txt
md_hierarchy-0.2.0.dist-info/top_level.txt
md_hierarchy-0.2.0.dist-info/RECORD
