Metadata-Version: 2.4
Name: md-hierarchy
Version: 0.2.0
Summary: Transform large markdown files into hierarchical folder structures for better navigation and AI-assisted editing
Author-email: Salih Ergut <salih.ergut@gmail.com>
License: MIT
Project-URL: Homepage, https://github.com/ergut/md-hierarchy
Project-URL: Repository, https://github.com/ergut/md-hierarchy
Project-URL: Issues, https://github.com/ergut/md-hierarchy/issues
Keywords: markdown,cli,hierarchy,documentation,llm,ai,split,merge
Classifier: Development Status :: 4 - Beta
Classifier: Intended Audience :: Developers
Classifier: License :: OSI Approved :: MIT License
Classifier: Programming Language :: Python :: 3
Classifier: Programming Language :: Python :: 3.8
Classifier: Programming Language :: Python :: 3.9
Classifier: Programming Language :: Python :: 3.10
Classifier: Programming Language :: Python :: 3.11
Classifier: Programming Language :: Python :: 3.12
Classifier: Topic :: Software Development :: Documentation
Classifier: Topic :: Text Processing :: Markup :: Markdown
Requires-Python: >=3.8
Requires-Dist: markdown-it-py>=3.0.0
Requires-Dist: click>=8.0.0
Provides-Extra: dev
Requires-Dist: pytest>=7.0.0; extra == "dev"
Requires-Dist: pytest-cov>=4.0.0; extra == "dev"
